playgroundrl_envs/exceptions.py
playgroundrl_envs/game_interface.py
playgroundrl_envs/sid_util.py
playgroundrl_envs/games/__init__.py
playgroundrl_envs/games/chess.py
playgroundrl_envs/games/coup.py
playgroundrl_envs/games/mining_decarbonization.py
playgroundrl_envs/games/petting_zoo.py
playgroundrl_envs/games/poker.py
playgroundrl_envs/games/snake.py
playgroundrl_envs/games/tic_tac_toe.py
playgroundrl_envs/games/catan/__init__.py
playgroundrl_envs/games/catan/catan.py
playgroundrl_envs/games/catan/encoder.py
playgroundrl_envs/games/codenames/__init__.py
playgroundrl_envs/games/codenames/codenames.py
playgroundrl_envs/games/codenames/wordlist.txt
playgroundrl_envs/games/go/__init__.py
playgroundrl_envs/games/go/go.py
playgroundrl_envs/games/go/engine/__init__.py
playgroundrl_envs/games/go/engine/gogame.py
playgroundrl_envs/games/go/engine/govars.py
playgroundrl_envs/games/go/engine/state_utils.py
playgroundrl_envs-0.0.18.dist-info/LICENSE.md
playgroundrl_envs-0.0.18.dist-info/METADATA
playgroundrl_envs-0.0.18.dist-info/WHEEL
playgroundrl_envs-0.0.18.dist-info/top_level.txt
playgroundrl_envs-0.0.18.dist-info/RECORD
