Metadata-Version: 2.1
Name: playgroundrl-envs
Version: 0.0.18
Summary: The environments hosted on Playground RL
Home-page: http://pypi.python.org/pypi/playgroundrl_envs/
Author: Rayan Krishnan
License-File: LICENSE.md
Requires-Dist: attrs ==22.2.0
Requires-Dist: AutoROM ==0.6.1
Requires-Dist: catanatron ==3.2.1
Requires-Dist: cattrs ==22.2.0
Requires-Dist: chess ==1.9.4
Requires-Dist: gymnasium ==0.28.1
Requires-Dist: numpy ==1.24.2
Requires-Dist: pettingzoo ==1.23.1
Requires-Dist: Pillow ==9.5.0
Requires-Dist: pygame ==2.4.0
Requires-Dist: scikit-learn ==1.2.2
Requires-Dist: scipy ==1.10.1
Requires-Dist: texasholdem ==0.9.0
Requires-Dist: nltk ==3.8.1
